tornet/__init__.py
tornet/banner.py
tornet/tornet.py
tornet/utils.py
tornet-2.0.2.dist-info/licenses/LICENSE
tornet-2.0.2.dist-info/METADATA
tornet-2.0.2.dist-info/WHEEL
tornet-2.0.2.dist-info/entry_points.txt
tornet-2.0.2.dist-info/top_level.txt
tornet-2.0.2.dist-info/RECORD
