Metadata-Version: 2.4
Name: tornet
Version: 2.0.2
Summary: Advanced Tor Network Controller for IP Rotation and Anonymity
Home-page: https://github.com/bytebreach/tornet
Author: ByteBreach
Author-email: ByteBreach <mrfidal@proton.me>
License: MIT
Project-URL: Homepage, https://github.com/bytebreach/tornet
Project-URL: Source, https://github.com/bytebreach/tornet
Project-URL: Issues, https://github.com/bytebreach/tornet/issues
Project-URL: Documentation, https://tornet.readthedocs.io/
Keywords: tor,anonymity,privacy,security,proxy,networking,ip-rotation
Classifier: Development Status :: 5 - Production/Stable
Classifier: Environment :: Console
Classifier: Intended Audience :: System Administrators
Classifier: Intended Audience :: Information Technology
Classifier: License :: OSI Approved :: MIT License
Classifier: Operating System :: POSIX :: Linux
Classifier: Programming Language :: Python :: 3
Classifier: Programming Language :: Python :: 3 :: Only
Classifier: Topic :: Security
Classifier: Topic :: Internet :: Proxy Servers
Classifier: Topic :: System :: Networking
Requires-Python: >=3.6
License-File: LICENSE
Requires-Dist: requests>=2.28.0
Requires-Dist: PySocks>=1.7.1
Requires-Dist: PyYAML>=6.0
Requires-Dist: schedule>=1.1.0
Requires-Dist: stem>=1.8.0
Dynamic: author
Dynamic: home-page
Dynamic: license-file
Dynamic: requires-python
